wafpd/__init__.py
wafpd/wafpd.py
wafpd-0.0.3.dist-info/METADATA
wafpd-0.0.3.dist-info/WHEEL
wafpd-0.0.3.dist-info/top_level.txt
wafpd-0.0.3.dist-info/RECORD
