Metadata-Version: 2.1
Name: wafpd
Version: 0.0.3
Summary: Command analyzer for pandas new versin
Author: WAFPD team
Author-email: giokhvichia69@gmail.com
Keywords: python,data,analyze,information
Classifier: Development Status :: 1 - Planning
Classifier: Intended Audience :: Developers
Classifier: Programming Language :: Python :: 3
Classifier: Operating System :: Microsoft :: Windows
Requires-Dist: nltk
Requires-Dist: pandas
